django_swingtime-3.0.0.dist-info/licenses/LICENSE
swingtime/__init__.py
swingtime/admin.py
swingtime/apps.py
swingtime/base_forms.py
swingtime/base_models.py
swingtime/conf.py
swingtime/context_processors.py
swingtime/forms.py
swingtime/models.py
swingtime/urls.py
swingtime/utils.py
swingtime/views.py
swingtime/locale/en/LC_MESSAGES/django.mo
swingtime/locale/en/LC_MESSAGES/django.po
swingtime/migrations/0001_initial.py
swingtime/migrations/0002_alter_occurrence_options_alter_event_id_and_more.py
swingtime/migrations/__init__.py
django_swingtime-3.0.0.dist-info/METADATA
django_swingtime-3.0.0.dist-info/WHEEL
django_swingtime-3.0.0.dist-info/top_level.txt
django_swingtime-3.0.0.dist-info/RECORD
